<annotation>
	<folder>dataset</folder>
	<filename>0017.png</filename>
	<path>/home/enes/Desktop/dataset/0017.png</path>
	<source>
		<database>Unknown</database>
	</source>
	<size>
		<width>848</width>
		<height>464</height>
		<depth>3</depth>
	</size>
	<segmented>0</segmented>
	<object>
		<name>gate</name>
		<pose>Unspecified</pose>
		<truncated>0</truncated>
		<difficult>0</difficult>
		<bndbox>
			<xmin>447</xmin>
			<ymin>141</ymin>
			<xmax>790</xmax>
			<ymax>462</ymax>
		</bndbox>
	</object>
</annotation>
