<annotation>
	<folder>dataset</folder>
	<filename>0121.png</filename>
	<path>/home/enes/Desktop/dataset/0121.png</path>
	<source>
		<database>Unknown</database>
	</source>
	<size>
		<width>1250</width>
		<height>703</height>
		<depth>3</depth>
	</size>
	<segmented>0</segmented>
	<object>
		<name>gate</name>
		<pose>Unspecified</pose>
		<truncated>0</truncated>
		<difficult>0</difficult>
		<bndbox>
			<xmin>99</xmin>
			<ymin>6</ymin>
			<xmax>874</xmax>
			<ymax>431</ymax>
		</bndbox>
	</object>
</annotation>
